py_parry3d/__init__.py
py_parry3d/_internal.cpython-311-i386-linux-musl.so
py_parry3d/_internal.pyi
py_parry3d/py.typed
py_parry3d-0.0.1.dist-info/METADATA
py_parry3d-0.0.1.dist-info/WHEEL
py_parry3d.libs/libgcc_s-f5fcfe20.so.1
py_parry3d-0.0.1.dist-info/RECORD
