Metadata-Version: 2.4
Name: py-parry3d
Version: 0.0.1
Classifier: Programming Language :: Rust
Classifier: Programming Language :: Python :: Implementation :: CPython
Requires-Dist: numpy>=1.26.4
Requires-Dist: maturin>=1.7.4 ; extra == 'dev'
Requires-Dist: pytest ; extra == 'test'
Requires-Dist: scipy>=1.14 ; extra == 'test'
Requires-Dist: trimesh ; extra == 'test'
Provides-Extra: dev
Provides-Extra: test
Summary: Python bindings for parry3d collision detection, optimized for batch operations
License-Expression: MIT
Requires-Python: >=3.11
